LICENSE
pytailor/__init__.py
pytailor/api/__init__.py
pytailor/api/account.py
pytailor/api/base.py
pytailor/api/dag.py
pytailor/api/fileset.py
pytailor/api/local_files.py
pytailor/api/parameterization.py
pytailor/api/project.py
pytailor/api/schema/__init__.py
pytailor/api/schema/description.py
pytailor/api/schema/files_schema.py
pytailor/api/schema/inputs_schema.py
pytailor/api/schema/strategies/__init__.py
pytailor/api/schema/strategies/additionalProperties.py
pytailor/api/schema/strategies/tailorschemabuilder.py
pytailor/api/workflow.py
pytailor/api/workflow_definition.py
pytailor/cli/__init__.py
pytailor/cli/main.py
pytailor/clients/__init__.py
pytailor/clients/async_rest_client.py
pytailor/clients/auth.py
pytailor/clients/file_client.py
pytailor/clients/handling.py
pytailor/clients/rest_client.py
pytailor/config.py
pytailor/exceptions.py
pytailor/execution/__init__.py
pytailor/execution/serialrunner.py
pytailor/execution/taskrunner.py
pytailor/execution/worker.py
pytailor/execution/worker_checks.py
pytailor/models.py
pytailor/utils.py
pytailor-0.8.4.dist-info/LICENSE
pytailor-0.8.4.dist-info/METADATA
pytailor-0.8.4.dist-info/WHEEL
pytailor-0.8.4.dist-info/entry_points.txt
pytailor-0.8.4.dist-info/RECORD
