Metadata-Version: 2.1
Name: pytailor
Version: 0.8.4
Summary: pyTailor orchestrates your existing python code as *workflows*
Home-page: https://github.com/entailor/pytailor/
License: BSD-3-Clause
Author: Audun Gravdal Johansen
Author-email: audun@entail.no
Requires-Python: >=3.9,<3.12
Classifier: License :: OSI Approved :: BSD License
Classifier: Programming Language :: Python :: 3
Classifier: Programming Language :: Python :: 3.9
Classifier: Programming Language :: Python :: 3.10
Classifier: Programming Language :: Python :: 3.11
Requires-Dist: click (>=8.1.6,<9.0.0)
Requires-Dist: genson (>=1.2.2,<2.0.0)
Requires-Dist: httpx (>=0.24.1,<0.25.0)
Requires-Dist: jsonpath-ng (>=1.5.2,<2.0.0)
Requires-Dist: pydantic (>=1.5.1,<2.0.0)
Requires-Dist: requests (>=2.31.0,<3.0.0)
Requires-Dist: toml (>=0.10.1,<0.11.0)
Project-URL: Repository, https://github.com/entailor/pytailor/
